pyMUMPS/__init__.py
mode_pymumps-0.1.0.dist-info/METADATA
mode_pymumps-0.1.0.dist-info/WHEEL
mode_pymumps-0.1.0.dist-info/top_level.txt
mode_pymumps-0.1.0.dist-info/RECORD
