Metadata-Version: 2.4
Name: mode-pymumps
Version: 0.1.0
Summary: Python bindings for MUMPS
Author-email: Your Name <you@example.com>
License: MIT
Requires-Python: >=3.9
Requires-Dist: scipy
Requires-Dist: numpy
